webwizard/__init__.py
webwizard/webwizard.py
webwizard-0.0.4.dist-info/LICENSE
webwizard-0.0.4.dist-info/METADATA
webwizard-0.0.4.dist-info/WHEEL
webwizard-0.0.4.dist-info/top_level.txt
webwizard-0.0.4.dist-info/RECORD
