Metadata-Version: 2.1
Name: webwizard
Version: 0.0.4
Summary: A python module to aid and automate CTF web challenges.
Home-page: https://github.com/Magicks52/webwizard
Author: John Nguyen
Author-email: jnguyensac@gmail.com
Classifier: Programming Language :: Python :: 3
Classifier: License :: OSI Approved :: MIT License
Classifier: Operating System :: Unix
Requires-Python: >=3.6
License-File: LICENSE
